activeft/__init__.py
activeft/acquisition_functions/__init__.py
activeft/acquisition_functions/bace.py
activeft/acquisition_functions/cosine_similarity.py
activeft/acquisition_functions/ctl.py
activeft/acquisition_functions/eig.py
activeft/acquisition_functions/information_density.py
activeft/acquisition_functions/itl.py
activeft/acquisition_functions/itl_noiseless.py
activeft/acquisition_functions/kmeans_pp.py
activeft/acquisition_functions/lazy_vtl.py
activeft/acquisition_functions/least_confidence.py
activeft/acquisition_functions/max_dist.py
activeft/acquisition_functions/max_entropy.py
activeft/acquisition_functions/min_margin.py
activeft/acquisition_functions/mm_itl.py
activeft/acquisition_functions/random.py
activeft/acquisition_functions/uncertainty_sampling.py
activeft/acquisition_functions/undirected_itl.py
activeft/acquisition_functions/undirected_vtl.py
activeft/acquisition_functions/vtl.py
activeft/active_data_loader.py
activeft/data.py
activeft/embeddings/__init__.py
activeft/embeddings/classification.py
activeft/embeddings/empirical_ntk.py
activeft/gaussian.py
activeft/model.py
activeft/models/simple_convnet.py
activeft/models/simple_mlp.py
activeft/sift.py
activeft/utils.py
activeft-0.1.1.dist-info/LICENSE
activeft-0.1.1.dist-info/METADATA
activeft-0.1.1.dist-info/WHEEL
activeft-0.1.1.dist-info/RECORD
