Metadata-Version: 2.1
Name: activeft
Version: 0.1.1
Summary: Efficiently fine-tune large neural networks by intelligent active data selection
License: MIT
Author: Jonas Hübotter
Author-email: jonas.huebotter@inf.ethz.ch
Requires-Python: >=3.10
Classifier: Development Status :: 4 - Beta
Classifier: Intended Audience :: Science/Research
Classifier: License :: OSI Approved :: MIT License
Classifier: Programming Language :: Python :: 3
Classifier: Programming Language :: Python :: 3.10
Classifier: Programming Language :: Python :: 3.11
Classifier: Programming Language :: Python :: 3.12
Classifier: Programming Language :: Python :: 3.13
Provides-Extra: logging
Requires-Dist: torch (>=2.4.0,<3.0.0)
Project-URL: homepage, https://github.com/jonhue/activeft
